[{"user":"Tywin","text":"The Lion doesn't concern himself with the opinion of the sheep!","id":"9f08680d-d82c-459e-9ebd-ef30fb613193","added":"2026-02-21T03:28:56.131Z"},{"user":"Eddard","text":"Winter is coming.","id":"544537f4-73a6-47ae-8832-4775e64e02e2","added":"2026-02-21T05:24:54.297Z"},{"user":"Peter","text":"Knowledge is power.","id":"4e873fd8-c04b-49dd-8165-79ec6eb1aed1","added":"2026-02-21T05:34:22.122Z"},{"user":"Steve","text":"I can do this all day.","id":"d96fc30d-d3fb-4267-bfa7-dfe8834032d6","added":"2026-02-23T20:38:58.144Z"},{"user":"Tony","text":"I, am, Iron man.","id":"3af5ae8c-cb6e-4d3b-b304-69090ea36410","added":"2026-02-23T20:39:30.099Z"}]